{
  "AI": [],
  "Markets": [],
  "Policy": [],
  "Technology": [],
  "World": [
    {
      "id": "5fc40f36569490787806e5ecee8fa78c",
      "title": "Lords back UK social media ban for under-16s",
      "url": "https://www.bbc.com/news/articles/cz0pnekxpn8o?at_medium=RSS&at_campaign=rss",
      "source": "BBC",
      "topic": "World",
      "priority": 65,
      "minutes_ago": 20,
      "timestamp": "2026-01-21T21:54:54.961006+00:00",
      "expires_at": "2026-01-21T23:54:54.961006+00:00"
    }
  ]
}